.gitignore
.travis.yml
CONTRIBUTING.md
COPYING
MANIFEST.in
README.rst
alembic.ini
changelog
requirements
setup.py
alembic/README
alembic/env.py
alembic/env.pyc
alembic/script.py.mako
alembic/versions/3ae0783e86c6_add_subcategories.py
alembic/versions/3ae0783e86c6_add_subcategories.pyc
bdgt/__init__.py
bdgt/application.py
bdgt/config.py
bdgt/models.py
bdgt.egg-info/PKG-INFO
bdgt.egg-info/SOURCES.txt
bdgt.egg-info/dependency_links.txt
bdgt.egg-info/requires.txt
bdgt.egg-info/top_level.txt
bdgt/commands/__init__.py
bdgt/commands/accounts.py
bdgt/commands/budget.py
bdgt/commands/categories.py
bdgt/commands/config.py
bdgt/commands/factory.py
bdgt/commands/importer.py
bdgt/commands/transactions.py
bdgt/importer/__init__.py
bdgt/importer/parsers.py
bdgt/importer/types.py
bdgt/storage/__init__.py
bdgt/storage/database.py
bdgt/storage/gateway.py
bin/bdgt
features/accounts.feature
features/budget.feature
features/categories.feature
features/config.feature
features/environment.py
features/import.feature
features/reconcile.feature
features/transactions.feature
features/steps/accounts.py
features/steps/budget.py
features/steps/categories.py
features/steps/commands.py
features/steps/system.py
features/steps/transactions.py
tests/__init__.py
tests/test_account_commands.py
tests/test_category_commands.py
tests/test_import_commands.py
tests/test_import_parser_csv_ing.py
tests/test_import_parser_factory.py
tests/test_import_parser_mt940.py
tests/test_import_parser_ofx.py
tests/test_models.py
tests/test_tx_commands.py