Metadata-Version: 1.1
Name: bdgt
Version: 6
Summary: A command line budget application
Home-page: https://github.com/jonblack/bdgt/
Author: Jon Black
Author-email: jon_black@mm.st
License: GPLv3
Keywords: budget finance command-line console
Platform: UNKNOWN
Classifier: Development Status :: 4 - Beta
Classifier: Environment :: Console
Classifier: Intended Audience :: End Users/Desktop
Classifier: License :: OSI Approved :: GNU General Public License v3 (GPLv3)
Classifier: Operating System :: OS Independent
Classifier: Programming Language :: Python
Classifier: Topic :: Office/Business :: Financial
